setup.cfg
setup.py
stock_data/__init__.py
stock_data/alpha.py
stock_data/beta.py
stock_data/cagr_ratio.py
stock_data/calmar_ratio.py
stock_data/current_price.py
stock_data/main.py
stock_data/max_drawdown.py
stock_data/momentum.py
stock_data/ols_stats.py
stock_data/r_squared.py
stock_data/ratios.py
stock_data/recent_news.py
stock_data/rolling_sharpe.py
stock_data/rolling_sortino.py
stock_data/rsi.py
stock_data/sentiment_value.py
stock_data/sortino.py
stock_data/test_risk_adjusted_metrics.py
stock_data/test_risk_metrics.py
stock_data/tickers.py
stock_data/value_at_risk.py
stock_data/volatility.py
stock_data/yahoo_recs.py
stock_data.egg-info/PKG-INFO
stock_data.egg-info/SOURCES.txt
stock_data.egg-info/dependency_links.txt
stock_data.egg-info/not-zip-safe
stock_data.egg-info/top_level.txt