Metadata-Version: 1.0
Name: stock-data
Version: 0.0
Summary: Get stock information effortlessly!
Home-page: UNKNOWN
Author: UNKNOWN
Author-email: shashank.vemuri1@gmail.com
License: UNKNOWN
Platform: UNKNOWN
